{
  "hash": "52593997",
  "configHash": "1a67390c",
  "lockfileHash": "c66c5dc7",
  "browserHash": "19eb6162",
  "optimized": {
    "vue": {
      "src": "../../node_modules/vue/dist/vue.runtime.esm-bundler.js",
      "file": "vue.js",
      "fileHash": "fcbf2a59",
      "needsInterop": false
    },
    "pinia": {
      "src": "../../node_modules/pinia/dist/pinia.mjs",
      "file": "pinia.js",
      "fileHash": "2b74bf2b",
      "needsInterop": false
    },
    "vue-router": {
      "src": "../../node_modules/vue-router/dist/vue-router.mjs",
      "file": "vue-router.js",
      "fileHash": "f7bd14f7",
      "needsInterop": false
    }
  },
  "chunks": {
    "chunk-Y7BMUUBP": {
      "file": "chunk-Y7BMUUBP.js"
    }
  }
}